ssenv/__init__.py
ssenv/main.py
ssenv-1.0.1.dist-info/LICENSE
ssenv-1.0.1.dist-info/METADATA
ssenv-1.0.1.dist-info/WHEEL
ssenv-1.0.1.dist-info/top_level.txt
ssenv-1.0.1.dist-info/RECORD
