Metadata-Version: 2.1
Name: ssenv
Version: 1.0.1
Summary: Super Duper Simple dotenv (.env) handler
Home-page: https://github.com/asheswook/Environment
Author: Jaewook Lee
Author-email: me@jwlee.xyz
Project-URL: Bug Tracker, https://github.com/asheswook/Environment/issues
Classifier: Programming Language :: Python :: 3
Classifier: License :: OSI Approved :: MIT License
Classifier: Operating System :: OS Independent
Requires-Python: >=3.0
License-File: LICENSE
